image_montage/__init__.py
image_montage/conversors.py
image_montage/montage.py
image_montage/objects.py
image_montage/settings.py
image_montage-1.0.2.dist-info/METADATA
image_montage-1.0.2.dist-info/WHEEL
image_montage-1.0.2.dist-info/top_level.txt
image_montage-1.0.2.dist-info/RECORD
