Metadata-Version: 2.1
Name: image-montage
Version: 1.0.2
Requires-Dist: opencv-python
Requires-Dist: numpy
Requires-Dist: pathlib
